feed2maildir/__init__.py
feed2maildir/converter.py
feed2maildir/loader.py
feed2maildir/reader.py
feed2maildir-0.3.8.data/scripts/feed2maildir
feed2maildir-0.3.8.dist-info/LICENSE
feed2maildir-0.3.8.dist-info/METADATA
feed2maildir-0.3.8.dist-info/WHEEL
feed2maildir-0.3.8.dist-info/top_level.txt
feed2maildir-0.3.8.dist-info/RECORD
