Metadata-Version: 2.1
Name: feed2maildir
Version: 0.3.8
Summary: Convert feeds to maildirs
Home-page: https://github.com/sulami/feed2maildir
Author: Robin Schroer
Author-email: sulami@peerwire.org
License: ISC
Platform: UNKNOWN
Classifier: Development Status :: 4 - Beta
Classifier: License :: OSI Approved :: ISC License (ISCL)
Classifier: Environment :: Console
Classifier: Intended Audience :: End Users/Desktop
Classifier: Natural Language :: English
Classifier: Operating System :: OS Independent
Classifier: Programming Language :: Python
Classifier: Topic :: Communications :: Email
Classifier: Topic :: Internet
Classifier: Topic :: Utilities
Requires-Dist: feedparser (>=5.1.3)
Requires-Dist: python-dateutil (>=2.2)
